{
  "$schema": "https://developer.joomla.org/schemas/json-schema/web_assets.json",
  "name": "plg_system_jooa11y",
  "version": "4.0.0",
  "description": "Joomla CMS",
  "license": "GPL-2.0-or-later",
  "assets": [
    {
      "name": "plg_system_jooa11y.jooa11y",
      "type": "style",
      "uri": "plg_system_jooa11y/jooa11y.min.css",
      "version": "5f6d1e166abece6ecae26d199338e3fd33c8a37b"
    },
    {
      "name": "plg_system_jooa11y.jooa11y-es5",
      "type": "script",
      "uri": "plg_system_jooa11y/jooa11y-es5.min.js",
      "dependencies": [
        "core"
      ],
      "attributes": {
        "defer": true,
        "nomodule": true
      },
      "version": "83c111eb30b6940e2884e43507bc94e8b289bfc2"
    },
    {
      "name": "plg_system_jooa11y.jooa11y",
      "type": "script",
      "uri": "plg_system_jooa11y/jooa11y.min.js",
      "dependencies": [
        "plg_system_jooa11y.jooa11y-es5"
      ],
      "attributes": {
        "type": "module"
      },
      "version": "8c0c7195ffd2a8530a7730b5c64e12bf69523eb4"
    }
  ]
}